bikeability/__init__.py
bikeability/bikeability.py
bikeability/grid.py
bikeability/osm.py
bikeability/settings.py
bikeability/util.py
bikeability-1.0.3.dist-info/METADATA
bikeability-1.0.3.dist-info/WHEEL
bikeability-1.0.3.dist-info/licenses/LICENSE
bikeability-1.0.3.dist-info/RECORD
