Metadata-Version: 2.4
Name: bikeability
Version: 1.0.3
Summary: A Package to derive bike-friendliness from OpenStreetMap data
Project-URL: Documentation, https://bikeability.readthedocs.io/
Project-URL: Source, https://github.com/DLR-VF/bikeability
Project-URL: Bug Tracker, https://github.com/DLR-VF/bikeability/issues
Author-email: "German Aerospace Center - DLR (Simon Nieland)" <simon.nieland@dlr.de>
License: MIT
License-File: LICENSE
Requires-Python: >=3.10
Requires-Dist: fiona>=1.10.1
Requires-Dist: geopandas>=1.1.1
Requires-Dist: h3>=4.3.1
Requires-Dist: osmnx>=2.0.6
Requires-Dist: requests>=2.32.4
Requires-Dist: scikit-learn>=1.7.1
